MANIFEST.in
README.md
README.rst
setup.py
skstan/__init__.py
skstan/base.py
skstan.egg-info/PKG-INFO
skstan.egg-info/SOURCES.txt
skstan.egg-info/dependency_links.txt
skstan.egg-info/requires.txt
skstan.egg-info/top_level.txt
skstan/regression/__init__.py
skstan/regression/base.py
skstan/regression/linear_models/__init__.py
skstan/regression/linear_models/linear_models.py
skstan/utils/__init__.py
skstan/utils/functions.py