Metadata-Version: 1.1
Name: skstan
Version: 0.0.0.dev2
Summary: Various bayesian models based on stan and pystan with a elegant interface like a scikit-learn or keras.
Home-page: https://skstan.org/latest/doc/
Author: scikit-stan development team
Author-email: scikit-stan@googlegroups.com
License: MIT
Platform: UNKNOWN
Classifier: Intended Audience :: Developers
Classifier: Intended Audience :: Science/Research
Classifier: Programming Language :: Python
Classifier: Programming Language :: Python :: 3.6
Classifier: Topic :: Scientific/Engineering :: Mathematics
